basex/__init__.py
basex/common/__init__.py
basex/common/cryptutils.py
basex/common/objectutils.py
basex/common/stringutils.py
basex/config/__init__.py
basex/config/content.py
basex/core/__init__.py
basex/core/background.py
basex/core/entity.py
basex/core/enums.py
basex/core/logstash.py
basex/core/service.py
basex/db/__init__.py
basex/db/decorator.py
basex/db/mapper.py
basex/db/sequence.py
basex/db/session.py
x_api_base-0.3.0.dist-info/LICENSE
x_api_base-0.3.0.dist-info/METADATA
x_api_base-0.3.0.dist-info/WHEEL
x_api_base-0.3.0.dist-info/top_level.txt
x_api_base-0.3.0.dist-info/RECORD
