Metadata-Version: 2.1
Name: x-api-base
Version: 0.3.0
Summary: base package for x-api
Home-page: https://github.com/yinziyan1206/x-base
Author: ziyan.yin
Author-email: 408856732@qq.com
License: BSD 2-Clause
Keywords: api,x-api,x-api-base
Platform: UNKNOWN
Classifier: Intended Audience :: Developers
Classifier: Programming Language :: Python :: 3 :: Only
Classifier: Programming Language :: Python :: 3.6
Classifier: Programming Language :: Python :: 3.7
Classifier: Programming Language :: Python :: 3.8
Classifier: Programming Language :: Python :: 3.9
Classifier: Programming Language :: Python :: 3.10
Classifier: Operating System :: OS Independent
Classifier: Environment :: Web Environment
Classifier: Development Status :: 3 - Alpha
Classifier: Topic :: Internet
Classifier: Topic :: Software Development :: Libraries :: Application Frameworks
Requires-Dist: orjson
Requires-Dist: loguru
Requires-Dist: PyYAML
Requires-Dist: pydantic
Requires-Dist: sqlalchemy (>=1.4)
